{
  "version": "1",
  "id": "b4c9686e479741fd836e1e68451701f5",
  "experiment": {
    "base": {
      "analysis": {
        "variableFilters": [],
        "selectedType": "dynamic",
        "choices": [
          {
            "type": "dynamic",
            "parameters": {
              "final_time": 3600.0
            },
            "simulationOptions": {},
            "solverOptions": {},
            "compilerOptions": {},
            "runtimeOptions": {}
          },
          {
            "type": "steady state",
            "parameters": {},
            "simulationOptions": {},
            "solverOptions": {},
            "compilerOptions": {},
            "runtimeOptions": {}
          }
        ]
      },
      "modifiers": {
        "variables": []
      }
    }
  },
  "metadata": {
    "created": "2023-11-13T00:04:24.101Z",
    "lastModified": "2023-11-13T00:04:24.101Z",
    "name": "Experiment 1"
  }
}